rungunicorn/__init__.py
rungunicorn/management/__init__.py
rungunicorn/management/commands/__init__.py
rungunicorn/management/commands/rungunicorn.py
rungunicorn-0.1.0.dist-info/WHEEL
rungunicorn-0.1.0.dist-info/METADATA
rungunicorn-0.1.0.dist-info/RECORD
